spectatorconfig/__init__.py
netflix_spectator_pyconf-0.1.0.dist-info/METADATA
netflix_spectator_pyconf-0.1.0.dist-info/WHEEL
netflix_spectator_pyconf-0.1.0.dist-info/top_level.txt
netflix_spectator_pyconf-0.1.0.dist-info/RECORD
